aiohttpx/__init__.py
aiohttpx/_api.py
aiohttpx/api_client.py
aiohttpx/client.py
aiohttpx/proxy.py
aiohttpx/version.py
aiohttpx/cli/__init__.py
aiohttpx/configs/__init__.py
aiohttpx/configs/base.py
aiohttpx/imports/__init__.py
aiohttpx/imports/boto.py
aiohttpx/imports/classprops.py
aiohttpx/imports/pyd.py
aiohttpx/imports/soup.py
aiohttpx/schemas/__init__.py
aiohttpx/schemas/params.py
aiohttpx/schemas/proxies.py
aiohttpx/schemas/types.py
aiohttpx/sdk/__init__.py
aiohttpx/utils/__init__.py
aiohttpx/utils/helpers.py
aiohttpx/utils/imports.py
aiohttpx/utils/lazy.py
aiohttpx/utils/logs.py
aiohttpx-0.0.12.dist-info/LICENSE
aiohttpx-0.0.12.dist-info/METADATA
aiohttpx-0.0.12.dist-info/WHEEL
aiohttpx-0.0.12.dist-info/entry_points.txt
aiohttpx-0.0.12.dist-info/top_level.txt
aiohttpx-0.0.12.dist-info/RECORD
