Metadata-Version: 2.1
Name: aiohttpx
Version: 0.0.12
Summary: A Python Wrapper for httpx that combines the httpx.AsyncClient with the httpx.Client to allow both async and sync requests
Home-page: https://github.com/GrowthEngineAI/aiohttpx
Author: Tri Songz
Author-email: ts@growthengineai.com
License: MIT License
Classifier: Intended Audience :: Developers
Classifier: License :: OSI Approved :: MIT License
Classifier: Programming Language :: Python :: 3.7
Classifier: Topic :: Software Development :: Libraries
License-File: LICENSE
Requires-Dist: httpx
Requires-Dist: pydantic
Provides-Extra: cli
Requires-Dist: typer; extra == "cli"
